satproc/__init__.py
satproc/chips.py
satproc/console/extract_chips.py
satproc/console/filter.py
satproc/console/generalize.py
satproc/console/make_masks.py
satproc/console/match_histograms.py
satproc/console/polygonize.py
satproc/console/scale.py
satproc/console/smooth_stitch.py
satproc/console/spatial_filter.py
satproc/filter.py
satproc/histogram.py
satproc/masks.py
satproc/postprocess/generalize.py
satproc/postprocess/polygonize.py
satproc/postprocess/smooth.py
satproc/postprocess/spatial_filter.py
satproc/scale.py
satproc/utils.py
pysatproc-0.2.2.dist-info/LICENSE.txt
pysatproc-0.2.2.dist-info/METADATA
pysatproc-0.2.2.dist-info/WHEEL
pysatproc-0.2.2.dist-info/entry_points.txt
pysatproc-0.2.2.dist-info/RECORD
