Metadata-Version: 2.1
Name: pysatproc
Version: 0.2.2
Summary: Python library and CLI tools for processing geospatial imagery for ML
License: Apache-2.0
Author: Damián Silvani
Author-email: munshkr@gmail.com
Requires-Python: >=3.8,<3.11
Classifier: License :: OSI Approved :: Apache Software License
Classifier: Programming Language :: Python :: 3
Classifier: Programming Language :: Python :: 3.8
Classifier: Programming Language :: Python :: 3.9
Classifier: Programming Language :: Python :: 3.10
Requires-Dist: Fiona (>=1.8.21,<2.0.0)
Requires-Dist: Rtree (>=0.9.7,<0.10.0)
Requires-Dist: Shapely (>=1.8.1,<2.0.0)
Requires-Dist: numpy (>=1.22.2,<2.0.0)
Requires-Dist: opencv-python (>=4.5.5,<5.0.0)
Requires-Dist: packaging (>=21.3,<22.0)
Requires-Dist: pyproj (>=3.3.0,<4.0.0)
Requires-Dist: rasterio (>=1.3.6,<2.0.0)
Requires-Dist: scikit-image (>=0.19.2,<0.20.0)
Requires-Dist: scipy (>=1.8.0,<2.0.0)
Requires-Dist: tqdm (>=4.62.3,<5.0.0)
